{
  "anim_memorymatch_pointcenter_fast_02": [
    {
      "durationTime_ms": 99,
      "triggerTime_ms": 132,
      "Name": "LiftHeightKeyFrame",
      "heightVariability_mm": 0,
      "height_mm": 43.396845637141034
    },
    {
      "durationTime_ms": 33,
      "triggerTime_ms": 231,
      "Name": "LiftHeightKeyFrame",
      "heightVariability_mm": 0,
      "height_mm": 0.0
    },
    {
      "angleVariability_deg": 0,
      "angle_deg": -24.999999999999996,
      "triggerTime_ms": 0,
      "Name": "HeadAngleKeyFrame",
      "durationTime_ms": 99
    },
    {
      "angleVariability_deg": 0,
      "angle_deg": 2.6833212375640865,
      "triggerTime_ms": 99,
      "Name": "HeadAngleKeyFrame",
      "durationTime_ms": 66
    },
    {
      "angleVariability_deg": 0,
      "angle_deg": -11.842516899108885,
      "triggerTime_ms": 165,
      "Name": "HeadAngleKeyFrame",
      "durationTime_ms": 66
    },
    {
      "angleVariability_deg": 0,
      "angle_deg": -9.131083488464354,
      "triggerTime_ms": 231,
      "Name": "HeadAngleKeyFrame",
      "durationTime_ms": 99
    },
    {
      "durationTime_ms": 0,
      "faceCenterY": 13.91980418352887,
      "faceCenterX": 0.0,
      "Name": "ProceduralFaceKeyFrame",
      "faceScaleY": 1.0,
      "faceScaleX": 1.0,
      "rightEye": [
        -10.722937003573131,
        0.0,
        1.2220369777691873,
        0.9052803931751328,
        0.0,
        0.5,
        0.5,
        0.5,
        0.5,
        0.5,
        0.5,
        0.5,
        0.5,
        0.0,
        0.0,
        0.0,
        0.0,
        0.0,
        0.0
      ],
      "triggerTime_ms": 0,
      "faceAngle": 0.0,
      "leftEye": [
        11.557501681630121,
        0.0,
        1.214332921016245,
        0.9052803931751328,
        0.0,
        0.5,
        0.5,
        0.5,
        0.5,
        0.5,
        0.5,
        0.5,
        0.5,
        0.0,
        0.0,
        0.0,
        0.0,
        0.0,
        0.0
      ]
    },
    {
      "durationTime_ms": 0,
      "faceCenterY": 13.91980418352887,
      "faceCenterX": 0.0,
      "Name": "ProceduralFaceKeyFrame",
      "faceScaleY": 1.0,
      "faceScaleX": 1.0,
      "rightEye": [
        -10.722937003573131,
        0.0,
        1.2220369777691873,
        0.9052803931751328,
        0.0,
        0.5,
        0.5,
        0.5,
        0.5,
        0.5,
        0.5,
        0.5,
        0.5,
        0.0,
        0.0,
        0.0,
        0.0,
        0.0,
        0.0
      ],
      "triggerTime_ms": 33,
      "faceAngle": 0.0,
      "leftEye": [
        11.557501681630121,
        0.0,
        1.214332921016245,
        0.9052803931751328,
        0.0,
        0.5,
        0.5,
        0.5,
        0.5,
        0.5,
        0.5,
        0.5,
        0.5,
        0.0,
        0.0,
        0.0,
        0.0,
        0.0,
        0.0
      ]
    },
    {
      "durationTime_ms": 0,
      "faceCenterY": 13.91980418352887,
      "faceCenterX": 0.0,
      "Name": "ProceduralFaceKeyFrame",
      "faceScaleY": 0.5402402281110438,
      "faceScaleX": 1.011434555053711,
      "rightEye": [
        -10.722937003573131,
        0.0,
        1.2352443320357753,
        0.9351439137749935,
        0.0,
        0.19311449566967134,
        0.19311449566967134,
        0.19311449566967134,
        0.19311449566967134,
        0.19311449566967134,
        0.19311449566967134,
        0.19311449566967134,
        0.19311449566967134,
        0.0,
        0.0,
        0.0,
        0.0,
        0.0,
        0.0
      ],
      "triggerTime_ms": 99,
      "faceAngle": 0.0,
      "leftEye": [
        11.557501681630121,
        0.0,
        1.214332921016245,
        0.9189713982387389,
        0.0,
        0.19311449566967134,
        0.19311449566967134,
        0.19311449566967134,
        0.19311449566967134,
        0.19311449566967134,
        0.19311449566967134,
        0.19311449566967134,
        0.19311449566967134,
        0.0,
        0.0,
        0.0,
        0.0,
        0.0,
        0.0
      ]
    },
    {
      "durationTime_ms": 0,
      "faceCenterY": 4.8035390326163006,
      "faceCenterX": 0.0,
      "Name": "ProceduralFaceKeyFrame",
      "faceScaleY": 1.09123694896698,
      "faceScaleX": 1.09123694896698,
      "rightEye": [
        -10.722937003573131,
        0.0,
        1.3274190415078404,
        1.1435631654089347,
        0.0,
        0.2807476602844817,
        0.2807476602844817,
        0.2807476602844817,
        0.2807476602844817,
        0.2807476602844817,
        0.2807476602844817,
        0.2807476602844817,
        0.2807476602844817,
        0.0,
        0.0,
        0.0,
        0.0,
        0.0,
        0.0
      ],
      "triggerTime_ms": 165,
      "faceAngle": 0.0,
      "leftEye": [
        11.557501681630121,
        0.0,
        1.214332921016245,
        1.0145218059867998,
        0.0,
        0.2807476602844817,
        0.2807476602844817,
        0.2807476602844817,
        0.2807476602844817,
        0.2807476602844817,
        0.2807476602844817,
        0.2807476602844817,
        0.2807476602844817,
        0.0,
        0.0,
        0.0,
        0.0,
        0.0,
        0.0
      ]
    },
    {
      "durationTime_ms": 0,
      "faceCenterY": 11.505078975719984,
      "faceCenterX": 0.0,
      "Name": "ProceduralFaceKeyFrame",
      "faceScaleY": 1.198343276977539,
      "faceScaleX": 1.230525255203247,
      "rightEye": [
        -10.722937003573131,
        0.0,
        1.2220369777691873,
        0.9052803931751328,
        0.0,
        0.5,
        0.5,
        0.5,
        0.5,
        0.5,
        0.5,
        0.5,
        0.5,
        0.0,
        0.0,
        0.0,
        0.0,
        0.0,
        0.0
      ],
      "triggerTime_ms": 198,
      "faceAngle": 0.0,
      "leftEye": [
        11.557501681630121,
        0.0,
        1.214332921016245,
        0.9052803931751328,
        0.0,
        0.5,
        0.5,
        0.5,
        0.5,
        0.5,
        0.5,
        0.5,
        0.5,
        0.0,
        0.0,
        0.0,
        0.0,
        0.0,
        0.0
      ]
    },
    {
      "durationTime_ms": 0,
      "faceCenterY": 12.865760206254324,
      "faceCenterX": 0.0,
      "Name": "ProceduralFaceKeyFrame",
      "faceScaleY": 0.9439576263806253,
      "faceScaleX": 0.9798970220698371,
      "rightEye": [
        -10.722937003573131,
        0.0,
        1.2220369777691873,
        0.9052803931751328,
        0.0,
        0.5,
        0.5,
        0.5,
        0.5,
        0.5,
        0.5,
        0.5,
        0.5,
        0.0,
        0.0,
        0.0,
        0.0,
        0.0,
        0.0
      ],
      "triggerTime_ms": 264,
      "faceAngle": 0.0,
      "leftEye": [
        11.557501681630121,
        0.0,
        1.214332921016245,
        0.9052803931751328,
        0.0,
        0.5,
        0.5,
        0.5,
        0.5,
        0.5,
        0.5,
        0.5,
        0.5,
        0.0,
        0.0,
        0.0,
        0.0,
        0.0,
        0.0
      ]
    },
    {
      "durationTime_ms": 0,
      "faceCenterY": 13.91980418352887,
      "faceCenterX": 0.0,
      "Name": "ProceduralFaceKeyFrame",
      "faceScaleY": 1.0,
      "faceScaleX": 1.0,
      "rightEye": [
        -10.722937003573131,
        0.0,
        1.2220369777691873,
        0.9052803931751328,
        0.0,
        0.5,
        0.5,
        0.5,
        0.5,
        0.5,
        0.5,
        0.5,
        0.5,
        0.0,
        0.0,
        0.0,
        0.0,
        0.0,
        0.0
      ],
      "triggerTime_ms": 330,
      "faceAngle": 0.0,
      "leftEye": [
        11.557501681630121,
        0.0,
        1.214332921016245,
        0.9052803931751328,
        0.0,
        0.5,
        0.5,
        0.5,
        0.5,
        0.5,
        0.5,
        0.5,
        0.5,
        0.0,
        0.0,
        0.0,
        0.0,
        0.0,
        0.0
      ]
    },
    {
      "volume": 1.0,
      "audioName": [
        "Play__Robot_Vo__Gp_Mm_Pattern_Turn_Short"
      ],
      "Name": "RobotAudioKeyFrame",
      "probability": 1.0,
      "hasAlts": true,
      "triggerTime_ms": 165.0,
      "audioEventId": [
        928871515
      ]
    },
    {
      "event_id": "DEVICE_AUDIO_TRIGGER",
      "triggerTime_ms": 165.0,
      "Name": "EventKeyFrame"
    },
    {
      "durationTime_ms": 66.0,
      "speed": -40.0,
      "triggerTime_ms": 0.0,
      "Name": "BodyMotionKeyFrame",
      "radius_mm": "STRAIGHT"
    },
    {
      "durationTime_ms": 99.0,
      "speed": 41.0,
      "triggerTime_ms": 66.0,
      "Name": "BodyMotionKeyFrame",
      "radius_mm": "STRAIGHT"
    }
  ]
}