{
  "anim_explorer_driving01_turbo_01_head_angle_40": [
    {
      "angleVariability_deg": 0,
      "angle_deg": 44.57028388977051,
      "triggerTime_ms": 0,
      "Name": "HeadAngleKeyFrame",
      "durationTime_ms": 66
    },
    {
      "angleVariability_deg": 0,
      "angle_deg": 25.19003772735596,
      "triggerTime_ms": 66,
      "Name": "HeadAngleKeyFrame",
      "durationTime_ms": 99
    },
    {
      "angleVariability_deg": 0,
      "angle_deg": 45.0,
      "triggerTime_ms": 165,
      "Name": "HeadAngleKeyFrame",
      "durationTime_ms": 99
    },
    {
      "angleVariability_deg": 0,
      "angle_deg": 45.0,
      "triggerTime_ms": 264,
      "Name": "HeadAngleKeyFrame",
      "durationTime_ms": 462
    },
    {
      "angleVariability_deg": 0,
      "angle_deg": 21.316568374633793,
      "triggerTime_ms": 726,
      "Name": "HeadAngleKeyFrame",
      "durationTime_ms": 99
    },
    {
      "angleVariability_deg": 0,
      "angle_deg": 25.45085144042969,
      "triggerTime_ms": 825,
      "Name": "HeadAngleKeyFrame",
      "durationTime_ms": 198
    },
    {
      "durationTime_ms": 0,
      "faceCenterY": 0.0,
      "faceCenterX": 0.0,
      "Name": "ProceduralFaceKeyFrame",
      "faceScaleY": 1.0,
      "faceScaleX": 1.0,
      "rightEye": [
        -10.206374107265454,
        0.0,
        1.2220369777691873,
        0.9052803931751328,
        0.0,
        0.5,
        0.5,
        0.5,
        0.5,
        0.5,
        0.5,
        0.5,
        0.5,
        0.0,
        0.0,
        0.0,
        0.0,
        0.0,
        0.0
      ],
      "triggerTime_ms": 0,
      "faceAngle": 0.0,
      "leftEye": [
        9.169666010979592,
        0.0,
        1.214332921016245,
        0.9052803931751328,
        0.0,
        0.5,
        0.5,
        0.5,
        0.5,
        0.5,
        0.5,
        0.5,
        0.5,
        0.0,
        0.0,
        0.0,
        0.0,
        0.0,
        0.0
      ]
    },
    {
      "durationTime_ms": 0,
      "faceCenterY": 0.32417266637958525,
      "faceCenterX": 0.0,
      "Name": "ProceduralFaceKeyFrame",
      "faceScaleY": 0.9375005359630788,
      "faceScaleX": 1.0552767515182495,
      "rightEye": [
        -10.206374107265454,
        0.0,
        1.2461149451679268,
        0.9052803931751328,
        0.0,
        0.4669041556237693,
        0.4669041556237693,
        0.4669041556237693,
        0.4669041556237693,
        0.4669041556237693,
        0.4669041556237693,
        0.4669041556237693,
        0.4669041556237693,
        0.0,
        0.0,
        0.0,
        0.0,
        0.0,
        0.0
      ],
      "triggerTime_ms": 33,
      "faceAngle": 0.0,
      "leftEye": [
        9.169666010979592,
        0.0,
        1.2375754508634182,
        0.9052803931751328,
        0.0,
        0.4669041556237693,
        0.4669041556237693,
        0.4669041556237693,
        0.4669041556237693,
        0.4669041556237693,
        0.4669041556237693,
        0.4669041556237693,
        0.4669041556237693,
        0.0,
        0.0,
        0.0,
        0.0,
        0.0,
        0.0
      ]
    },
    {
      "durationTime_ms": 0,
      "faceCenterY": 7.939861178552975,
      "faceCenterX": 0.0,
      "Name": "ProceduralFaceKeyFrame",
      "faceScaleY": 0.0746653012631696,
      "faceScaleX": 1.818399429321289,
      "rightEye": [
        -10.206374107265454,
        0.0,
        1.578522208770766,
        0.9052803931751328,
        0.0,
        0.01,
        0.01,
        0.01,
        0.01,
        0.01,
        0.01,
        0.01,
        0.01,
        0.0,
        0.0,
        0.0,
        0.0,
        0.0,
        0.0
      ],
      "triggerTime_ms": 66,
      "faceAngle": 0.0,
      "leftEye": [
        9.169666010979592,
        0.0,
        1.5584491201178454,
        0.9052803931751328,
        0.0,
        0.01,
        0.01,
        0.01,
        0.01,
        0.01,
        0.01,
        0.01,
        0.01,
        0.0,
        0.0,
        0.0,
        0.0,
        0.0,
        0.0
      ]
    },
    {
      "durationTime_ms": 0,
      "faceCenterY": 9.506501727138643,
      "faceCenterX": 0.0,
      "Name": "ProceduralFaceKeyFrame",
      "faceScaleY": 0.0746653012631696,
      "faceScaleX": 1.818399429321289,
      "rightEye": [
        -10.206374107265454,
        0.0,
        1.578522208770766,
        0.9052803931751328,
        0.0,
        0.01,
        0.01,
        0.01,
        0.01,
        0.01,
        0.01,
        0.01,
        0.01,
        0.0,
        0.0,
        0.0,
        0.0,
        0.0,
        0.0
      ],
      "triggerTime_ms": 99,
      "faceAngle": 0.0,
      "leftEye": [
        9.169666010979592,
        0.0,
        1.5584491201178454,
        0.9052803931751328,
        0.0,
        0.01,
        0.01,
        0.01,
        0.01,
        0.01,
        0.01,
        0.01,
        0.01,
        0.0,
        0.0,
        0.0,
        0.0,
        0.0,
        0.0
      ]
    },
    {
      "durationTime_ms": 0,
      "faceCenterY": 6.4828013555680295,
      "faceCenterX": 0.0,
      "Name": "ProceduralFaceKeyFrame",
      "faceScaleY": 0.0746653012631696,
      "faceScaleX": 1.818399429321289,
      "rightEye": [
        -10.206374107265454,
        0.0,
        1.578522208770766,
        0.9052803931751328,
        0.0,
        0.01,
        0.01,
        0.01,
        0.01,
        0.01,
        0.01,
        0.01,
        0.01,
        0.0,
        0.0,
        0.0,
        0.0,
        0.0,
        0.0
      ],
      "triggerTime_ms": 132,
      "faceAngle": 0.0,
      "leftEye": [
        9.169666010979592,
        0.0,
        1.5584491201178454,
        0.9052803931751328,
        0.0,
        0.01,
        0.01,
        0.01,
        0.01,
        0.01,
        0.01,
        0.01,
        0.01,
        0.0,
        0.0,
        0.0,
        0.0,
        0.0,
        0.0
      ]
    },
    {
      "durationTime_ms": 0,
      "faceCenterY": 0.0,
      "faceCenterX": 0.0,
      "Name": "ProceduralFaceKeyFrame",
      "faceScaleY": 0.3381009408510185,
      "faceScaleX": 1.156723141670227,
      "rightEye": [
        -10.206374107265454,
        0.0,
        1.4011665741505803,
        0.9052803931751328,
        0.0,
        0.12161771691736581,
        0.12161771691736581,
        0.12161771691736581,
        0.12161771691736581,
        0.12161771691736581,
        0.12161771691736581,
        0.12161771691736581,
        0.12161771691736581,
        0.0,
        0.0,
        0.0,
        0.0,
        0.0,
        0.0
      ],
      "triggerTime_ms": 165,
      "faceAngle": 0.0,
      "leftEye": [
        9.169666010979592,
        0.0,
        1.3872472256777757,
        0.9052803931751328,
        0.0,
        0.12161771691736581,
        0.12161771691736581,
        0.12161771691736581,
        0.12161771691736581,
        0.12161771691736581,
        0.12161771691736581,
        0.12161771691736581,
        0.12161771691736581,
        0.0,
        0.0,
        0.0,
        0.0,
        0.0,
        0.0
      ]
    },
    {
      "durationTime_ms": 0,
      "faceCenterY": 3.2387327238276957,
      "faceCenterX": 0.0,
      "Name": "ProceduralFaceKeyFrame",
      "faceScaleY": 1.2010478973388672,
      "faceScaleX": 1.2010478973388672,
      "rightEye": [
        -10.206374107265454,
        0.0,
        1.341900668897817,
        0.9797513841894556,
        0.0,
        0.5,
        0.5,
        0.5,
        0.5,
        0.5,
        0.5,
        0.5,
        0.5,
        0.0,
        0.0,
        0.0,
        0.0,
        0.0,
        0.0
      ],
      "triggerTime_ms": 198,
      "faceAngle": 0.0,
      "leftEye": [
        9.169666010979592,
        0.0,
        1.3300376801623603,
        0.9797513841894556,
        0.0,
        0.5,
        0.5,
        0.5,
        0.5,
        0.5,
        0.5,
        0.5,
        0.5,
        0.0,
        0.0,
        0.0,
        0.0,
        0.0,
        0.0
      ]
    },
    {
      "durationTime_ms": 0,
      "faceCenterY": -7.722928186798656,
      "faceCenterX": 1.46130627770695,
      "Name": "ProceduralFaceKeyFrame",
      "faceScaleY": 0.9789971707402552,
      "faceScaleX": 0.7950384608140884,
      "rightEye": [
        -10.206374107265454,
        0.0,
        1.341900668897817,
        0.9797513841894556,
        0.0,
        0.5,
        0.5,
        0.5,
        0.5,
        0.5,
        0.5,
        0.5,
        0.5,
        0.0,
        0.0,
        0.0,
        0.0,
        0.0,
        0.0
      ],
      "triggerTime_ms": 264,
      "faceAngle": 0.0,
      "leftEye": [
        9.169666010979592,
        0.0,
        1.3300376801623603,
        0.9797513841894556,
        0.0,
        0.5,
        0.5,
        0.5,
        0.5,
        0.5,
        0.5,
        0.5,
        0.5,
        0.0,
        0.0,
        0.0,
        0.0,
        0.0,
        0.0
      ]
    },
    {
      "durationTime_ms": 0,
      "faceCenterY": -6.004660767741268,
      "faceCenterX": 2.1037871713257705,
      "Name": "ProceduralFaceKeyFrame",
      "faceScaleY": 1.0997545719146729,
      "faceScaleX": 0.7121989719438819,
      "rightEye": [
        -7.851843341385922,
        2.393055397688045,
        1.391477089865027,
        0.9411667849836931,
        0.0,
        0.5,
        0.5,
        0.6296353880646919,
        0.5899468325938244,
        0.6380886872781275,
        0.7962938311796037,
        0.5,
        0.5,
        0.0,
        0.0,
        0.0,
        0.5147741389121547,
        0.0,
        0.0
      ],
      "triggerTime_ms": 297,
      "faceAngle": 0.0,
      "leftEye": [
        5.515369080498655,
        3.522611509141456,
        1.368168008147898,
        0.9928489042289925,
        0.0,
        0.5,
        0.5,
        0.6203644901411245,
        0.5899468325938244,
        0.5791097112625607,
        0.5899468325938244,
        0.5,
        0.5,
        0.0,
        0.0,
        0.0,
        0.5272859221679199,
        0.0,
        0.0
      ]
    },
    {
      "durationTime_ms": 0,
      "faceCenterY": -4.326187841056115,
      "faceCenterX": 2.2250011798123492,
      "Name": "ProceduralFaceKeyFrame",
      "faceScaleY": 1.0658072233200073,
      "faceScaleX": 0.7066526405525392,
      "rightEye": [
        -7.354734023169845,
        2.8982988509610554,
        1.4019441311568352,
        0.9330204200794014,
        0.0,
        0.5,
        0.5,
        0.6570052084920839,
        0.6089372250342429,
        0.6672432176560186,
        0.8588500744389158,
        0.5,
        0.5,
        0.0,
        0.0,
        0.0,
        0.6234580010277877,
        0.0,
        0.0
      ],
      "triggerTime_ms": 330,
      "faceAngle": 0.0,
      "leftEye": [
        4.743840459949408,
        4.266337431460216,
        1.3719449249589637,
        0.9942715370456199,
        0.0,
        0.5,
        0.5,
        0.6457769590775797,
        0.6089372250342429,
        0.5958120427676974,
        0.6089372250342429,
        0.5,
        0.5,
        0.0,
        0.0,
        0.0,
        0.6386113276476608,
        0.0,
        0.012443215959620238
      ]
    },
    {
      "durationTime_ms": 0,
      "faceCenterY": -2.6166086916676807,
      "faceCenterX": 2.2250011798123492,
      "Name": "ProceduralFaceKeyFrame",
      "faceScaleY": 1.1640572547912598,
      "faceScaleX": 0.8369688979302068,
      "rightEye": [
        -7.354734023169845,
        2.8982988509610554,
        1.4019441311568352,
        0.9330204200794014,
        0.0,
        0.5,
        0.5,
        0.6570052084920839,
        0.6089372250342429,
        0.6672432176560186,
        0.8588500744389158,
        0.5,
        0.5,
        0.0,
        0.0,
        0.0,
        0.6234580010277877,
        0.0,
        0.0
      ],
      "triggerTime_ms": 363,
      "faceAngle": 0.0,
      "leftEye": [
        4.743840459949408,
        4.266337431460216,
        1.3744907246520048,
        0.9954841839286246,
        0.0,
        0.5,
        0.5,
        0.6457769590775797,
        0.6089372250342429,
        0.5958120427676974,
        0.6089372250342429,
        0.5,
        0.5,
        0.0,
        0.0,
        0.0,
        0.6386113276476608,
        0.0,
        0.03981833113007251
      ]
    },
    {
      "durationTime_ms": 0,
      "faceCenterY": -0.7010814172179998,
      "faceCenterX": 2.2250011798123492,
      "Name": "ProceduralFaceKeyFrame",
      "faceScaleY": 1.1965649127960205,
      "faceScaleX": 0.911756216863373,
      "rightEye": [
        -7.354734023169845,
        2.8982988509610554,
        1.4019441311568352,
        0.9330204200794014,
        0.0,
        0.5,
        0.5,
        0.6570052084920839,
        0.6089372250342429,
        0.6672432176560186,
        0.8588500744389158,
        0.5,
        0.5,
        0.0,
        0.0,
        0.0,
        0.6234580010277877,
        0.0,
        0.04466139185212331
      ],
      "triggerTime_ms": 429,
      "faceAngle": 0.0,
      "leftEye": [
        4.743840459949408,
        4.266337431460216,
        1.3769073227820563,
        0.9973455599349563,
        0.0,
        0.5,
        0.5,
        0.6457769590775797,
        0.6089372250342429,
        0.5958120427676974,
        0.6089372250342429,
        0.5,
        0.5,
        0.0,
        0.0,
        0.0,
        0.6386113276476608,
        0.0,
        0.07963676240836438
      ]
    },
    {
      "durationTime_ms": 0,
      "faceCenterY": 0.1481550219317285,
      "faceCenterX": 2.2250011798123492,
      "Name": "ProceduralFaceKeyFrame",
      "faceScaleY": 1.1965649127960205,
      "faceScaleX": 0.9611497518174761,
      "rightEye": [
        -7.354734023169845,
        2.8982988509610554,
        1.4019441311568352,
        0.9330204200794014,
        0.0,
        0.5,
        0.5,
        0.6570052084920839,
        0.6089372250342429,
        0.6672432176560186,
        0.8588500744389158,
        0.5,
        0.5,
        0.0,
        0.0,
        0.0,
        0.6234580010277877,
        0.0,
        0.07136297670807247
      ],
      "triggerTime_ms": 693,
      "faceAngle": 0.0,
      "leftEye": [
        4.743840459949408,
        4.266337431460216,
        1.3882450244186124,
        0.9996808875181955,
        0.0,
        0.5,
        0.5,
        0.6457769590775797,
        0.6089372250342429,
        0.5958120427676974,
        0.6089372250342429,
        0.5,
        0.5,
        0.0,
        0.0,
        0.0,
        0.6386113276476608,
        0.0,
        0.07963676240836438
      ]
    },
    {
      "durationTime_ms": 0,
      "faceCenterY": 1.952412343509309,
      "faceCenterX": 2.0747188757169006,
      "Name": "ProceduralFaceKeyFrame",
      "faceScaleY": 1.1207889318466187,
      "faceScaleX": 1.0190505981445312,
      "rightEye": [
        -7.547340482744806,
        2.702540428058797,
        1.4138706377195143,
        0.9311467892200653,
        0.0,
        0.4669041556237693,
        0.4669041556237693,
        0.6133048317975245,
        0.5684834651416608,
        0.6228513307584755,
        0.8015165622920186,
        0.4669041556237693,
        0.4669041556237693,
        0.0,
        0.0,
        0.0,
        0.5813480274598267,
        0.0,
        0.06654291136444437
      ],
      "triggerTime_ms": 726,
      "faceAngle": 0.0,
      "leftEye": [
        5.0427721771481195,
        3.978178122333049,
        1.3997409413100566,
        0.9933047653086078,
        0.0,
        0.4669041556237693,
        0.4669041556237693,
        0.6028349425057975,
        0.5684834651416608,
        0.5562447965952373,
        0.5684834651416608,
        0.4669041556237693,
        0.4669041556237693,
        0.0,
        0.0,
        0.0,
        0.5954778947116668,
        0.0,
        0.07425790169450787
      ]
    },
    {
      "durationTime_ms": 0,
      "faceCenterY": 5.881289460920699,
      "faceCenterX": 0.0,
      "Name": "ProceduralFaceKeyFrame",
      "faceScaleY": 0.0746653012631696,
      "faceScaleX": 1.818399429321289,
      "rightEye": [
        -10.206374107265454,
        0.0,
        1.578522208770766,
        0.9052803931751328,
        0.0,
        0.01,
        0.01,
        0.01,
        0.01,
        0.01,
        0.01,
        0.01,
        0.01,
        0.0,
        0.0,
        0.0,
        0.0,
        0.0,
        0.0
      ],
      "triggerTime_ms": 759,
      "faceAngle": 0.0,
      "leftEye": [
        9.169666010979592,
        0.0,
        1.5584491201178454,
        0.9052803931751328,
        0.0,
        0.01,
        0.01,
        0.01,
        0.01,
        0.01,
        0.01,
        0.01,
        0.01,
        0.0,
        0.0,
        0.0,
        0.0,
        0.0,
        0.0
      ]
    },
    {
      "durationTime_ms": 0,
      "faceCenterY": 9.54655433013244,
      "faceCenterX": 0.0,
      "Name": "ProceduralFaceKeyFrame",
      "faceScaleY": 0.0746653012631696,
      "faceScaleX": 1.818399429321289,
      "rightEye": [
        -10.206374107265454,
        0.0,
        1.578522208770766,
        0.9052803931751328,
        0.0,
        0.01,
        0.01,
        0.01,
        0.01,
        0.01,
        0.01,
        0.01,
        0.01,
        0.0,
        0.0,
        0.0,
        0.0,
        0.0,
        0.0
      ],
      "triggerTime_ms": 792,
      "faceAngle": 0.0,
      "leftEye": [
        9.169666010979592,
        0.0,
        1.5584491201178454,
        0.9052803931751328,
        0.0,
        0.01,
        0.01,
        0.01,
        0.01,
        0.01,
        0.01,
        0.01,
        0.01,
        0.0,
        0.0,
        0.0,
        0.0,
        0.0,
        0.0
      ]
    },
    {
      "durationTime_ms": 0,
      "faceCenterY": 4.404012498615658,
      "faceCenterX": 0.0,
      "Name": "ProceduralFaceKeyFrame",
      "faceScaleY": 0.3512382515480343,
      "faceScaleX": 1.0,
      "rightEye": [
        -10.206374107265454,
        0.0,
        1.2220369777691873,
        0.9052803931751328,
        0.0,
        0.5,
        0.5,
        0.5,
        0.5,
        0.5,
        0.5,
        0.5,
        0.5,
        0.0,
        0.0,
        0.0,
        0.0,
        0.0,
        0.0
      ],
      "triggerTime_ms": 825,
      "faceAngle": 0.0,
      "leftEye": [
        9.169666010979592,
        0.0,
        1.214332921016245,
        0.9052803931751328,
        0.0,
        0.5,
        0.5,
        0.5,
        0.5,
        0.5,
        0.5,
        0.5,
        0.5,
        0.0,
        0.0,
        0.0,
        0.0,
        0.0,
        0.0
      ]
    },
    {
      "durationTime_ms": 0,
      "faceCenterY": -2.3545488822000307,
      "faceCenterX": 0.0,
      "Name": "ProceduralFaceKeyFrame",
      "faceScaleY": 1.0997189283370972,
      "faceScaleX": 0.9061689370411761,
      "rightEye": [
        -10.206374107265454,
        0.0,
        1.2220369777691873,
        0.9052803931751328,
        0.0,
        0.5,
        0.5,
        0.5,
        0.5,
        0.5,
        0.5,
        0.5,
        0.5,
        0.0,
        0.0,
        0.0,
        0.0,
        0.0,
        0.0
      ],
      "triggerTime_ms": 891,
      "faceAngle": 0.0,
      "leftEye": [
        9.169666010979592,
        0.0,
        1.214332921016245,
        0.9052803931751328,
        0.0,
        0.5,
        0.5,
        0.5,
        0.5,
        0.5,
        0.5,
        0.5,
        0.5,
        0.0,
        0.0,
        0.0,
        0.0,
        0.0,
        0.0
      ]
    },
    {
      "durationTime_ms": 0,
      "faceCenterY": -3.3715202343872948,
      "faceCenterX": 0.0,
      "Name": "ProceduralFaceKeyFrame",
      "faceScaleY": 0.9292311067084397,
      "faceScaleX": 0.8735890976910947,
      "rightEye": [
        -10.206374107265454,
        0.0,
        1.2220369777691873,
        0.9052803931751328,
        0.0,
        0.5,
        0.5,
        0.5,
        0.5,
        0.5,
        0.5,
        0.5,
        0.5,
        0.0,
        0.0,
        0.0,
        0.0,
        0.0,
        0.0
      ],
      "triggerTime_ms": 957,
      "faceAngle": 0.0,
      "leftEye": [
        9.169666010979592,
        0.0,
        1.214332921016245,
        0.9052803931751328,
        0.0,
        0.5,
        0.5,
        0.5,
        0.5,
        0.5,
        0.5,
        0.5,
        0.5,
        0.0,
        0.0,
        0.0,
        0.0,
        0.0,
        0.0
      ]
    },
    {
      "durationTime_ms": 0,
      "faceCenterY": -0.7046543492747562,
      "faceCenterX": 0.0,
      "Name": "ProceduralFaceKeyFrame",
      "faceScaleY": 0.7623533001974351,
      "faceScaleX": 0.9008945816068392,
      "rightEye": [
        -10.206374107265454,
        0.0,
        1.2220369777691873,
        0.9052803931751328,
        0.0,
        0.5,
        0.5,
        0.5,
        0.5,
        0.5,
        0.5,
        0.5,
        0.5,
        0.0,
        0.0,
        0.0,
        0.0,
        0.0,
        0.0
      ],
      "triggerTime_ms": 1056,
      "faceAngle": 0.0,
      "leftEye": [
        9.169666010979592,
        0.0,
        1.214332921016245,
        0.9052803931751328,
        0.0,
        0.5,
        0.5,
        0.5,
        0.5,
        0.5,
        0.5,
        0.5,
        0.5,
        0.0,
        0.0,
        0.0,
        0.0,
        0.0,
        0.0
      ]
    },
    {
      "durationTime_ms": 0,
      "faceCenterY": 0.0,
      "faceCenterX": 0.0,
      "Name": "ProceduralFaceKeyFrame",
      "faceScaleY": 1.0,
      "faceScaleX": 1.0,
      "rightEye": [
        -10.206374107265454,
        0.0,
        1.2220369777691873,
        0.9052803931751328,
        0.0,
        0.5,
        0.5,
        0.5,
        0.5,
        0.5,
        0.5,
        0.5,
        0.5,
        0.0,
        0.0,
        0.0,
        0.0,
        0.0,
        0.0
      ],
      "triggerTime_ms": 1287,
      "faceAngle": 0.0,
      "leftEye": [
        9.169666010979592,
        0.0,
        1.214332921016245,
        0.9052803931751328,
        0.0,
        0.5,
        0.5,
        0.5,
        0.5,
        0.5,
        0.5,
        0.5,
        0.5,
        0.0,
        0.0,
        0.0,
        0.0,
        0.0,
        0.0
      ]
    },
    {
      "volume": 1.0,
      "audioName": [
        "Play__Robot_Sfx__Mvt_Tread_Forward_Start"
      ],
      "Name": "RobotAudioKeyFrame",
      "probability": 1.0,
      "hasAlts": true,
      "triggerTime_ms": 0.0,
      "audioEventId": [
        2652548234
      ]
    },
    {
      "volume": 1.0,
      "audioName": [
        "Play__Robot_Sfx__Scrn_Surprised"
      ],
      "Name": "RobotAudioKeyFrame",
      "probability": 1.0,
      "hasAlts": true,
      "triggerTime_ms": 132.0,
      "audioEventId": [
        3774252557
      ]
    },
    {
      "volume": 1.0,
      "audioName": [
        "Play__Robot_Vo__Gp_Explorer_Drive_Start_Turbo"
      ],
      "Name": "RobotAudioKeyFrame",
      "probability": 1.0,
      "hasAlts": true,
      "triggerTime_ms": 264.0,
      "audioEventId": [
        403916659
      ]
    },
    {
      "volume": 1.0,
      "audioName": [
        "Play__Robot_Sfx__Srv_Surprised_Long"
      ],
      "Name": "RobotAudioKeyFrame",
      "probability": 1.0,
      "hasAlts": true,
      "triggerTime_ms": 363.0,
      "audioEventId": [
        3606017555
      ]
    },
    {
      "volume": 1.0,
      "audioName": [
        "Play__Robot_Sfx__Scrn_Curious_Short"
      ],
      "Name": "RobotAudioKeyFrame",
      "probability": 1.0,
      "hasAlts": true,
      "triggerTime_ms": 792.0,
      "audioEventId": [
        2929211683
      ]
    }
  ]
}